mossflow/TkinterWidgets.pyc
mossflow/__init__.py
mossflow/__init__.pyc
mossflow/clearcache.pyc
mossflow/gldemo.pyc
mossflow/numpyutils.pyc
mossflow/demos/__init__.py
mossflow/demos/__init__.pyc
mossflow/demos/main.pyc
mossflow/libs/dev/SR7Link.pyc
mossflow/libs/dev/64bit/SR7Link-en.h
mossflow/libs/dev/64bit/SR7Link.dll
mossflow/libs/dev/64bit/SR7Link.h
mossflow/libs/dev/64bit/SR7Link.lib
mossflow/libs/dev/64bit/SR7Link.pdb
mossflow/libs/dev/64bit/SR7Link25D.h
mossflow/libs/dev/64bit/frequency.ssp
mossflow/libs/pcl/Pcl_wapper.dll
mossflow/libs/pcl/Pcl_wapper.exp
mossflow/libs/pcl/Pcl_wapper.lib
mossflow/libs/pcl/Pcl_wapper.pdb
mossflow/libs/pcl/boost_filesystem-vc143-mt-gd-x64-1_86.dll
mossflow/libs/pcl/boost_iostreams-vc143-mt-gd-x64-1_86.dll
mossflow/libs/pcl/bz2d.dll
mossflow/libs/pcl/concrt140d.dll
mossflow/libs/pcl/liblzma.dll
mossflow/libs/pcl/libomp140.x86_64.dll
mossflow/libs/pcl/libomp140d.x86_64.dll
mossflow/libs/pcl/libpng16d.dll
mossflow/libs/pcl/lz4d.dll
mossflow/libs/pcl/msvcp140_1d.dll
mossflow/libs/pcl/msvcp140_2d.dll
mossflow/libs/pcl/msvcp140d.dll
mossflow/libs/pcl/msvcp140d_atomic_wait.dll
mossflow/libs/pcl/msvcp140d_codecvt_ids.dll
mossflow/libs/pcl/pcl_commond.dll
mossflow/libs/pcl/pcl_featuresd.dll
mossflow/libs/pcl/pcl_filtersd.dll
mossflow/libs/pcl/pcl_io_plyd.dll
mossflow/libs/pcl/pcl_iod.dll
mossflow/libs/pcl/pcl_kdtreed.dll
mossflow/libs/pcl/pcl_octreed.dll
mossflow/libs/pcl/pcl_recognitiond.dll
mossflow/libs/pcl/pcl_sample_consensusd.dll
mossflow/libs/pcl/pcl_searchd.dll
mossflow/libs/pcl/pointscloud.pyc
mossflow/libs/pcl/ucrtbased.dll
mossflow/libs/pcl/vcamp140d.dll
mossflow/libs/pcl/vccorlib140d.dll
mossflow/libs/pcl/vcomp140d.dll
mossflow/libs/pcl/vcruntime140_1d.dll
mossflow/libs/pcl/vcruntime140d.dll
mossflow/libs/pcl/zlibd1.dll
mossflow/libs/pcl/zstd.dll
mossflow/mossmodlues/__init__.py
mossflow/mossmodlues/__init__.pyc
mossflow/mossmodlues/default.flp
mossflow/mossmodlues/System/Graphics_AttributeExtraModule.pyc
mossflow-0.1.131.dist-info/METADATA
mossflow-0.1.131.dist-info/WHEEL
mossflow-0.1.131.dist-info/top_level.txt
mossflow-0.1.131.dist-info/RECORD
