Metadata-Version: 2.4
Name: mossflow
Version: 0.1.131
Summary: MossFlow: A tool for build your own data processing pipeline visually.
Author: EdenChen93
Author-email: 448217951@qq.com
License: Non-Commercial License
Requires-Python: >=3.12
Requires-Dist: certifi==2025.4.26
Requires-Dist: charset-normalizer==3.4.2
Requires-Dist: contourpy==1.3.2
Requires-Dist: cycler==0.12.1
Requires-Dist: fonttools==4.57.0
Requires-Dist: idna==3.10
Requires-Dist: kiwisolver==1.4.8
Requires-Dist: matplotlib==3.10.1
Requires-Dist: numpy==2.2.5
Requires-Dist: opencv-python==4.11.0.86
Requires-Dist: packaging==25.0
Requires-Dist: pillow==10.4.0
Requires-Dist: PyOpenGL==3.1.9
Requires-Dist: pyopengltk==0.0.4
Requires-Dist: pyparsing==3.2.3
Requires-Dist: python-dateutil==2.9.0.post0
Requires-Dist: requests==2.32.4
Requires-Dist: six==1.17.0
Requires-Dist: tifffile==2025.3.30
Requires-Dist: tkhtmlview==0.3.1
Requires-Dist: urllib3==2.4.0
Requires-Dist: pyglm==2.8.2
Requires-Dist: scipy==1.16.2
Dynamic: author
Dynamic: author-email
Dynamic: description
Dynamic: description-content-type
Dynamic: license
Dynamic: requires-dist
Dynamic: requires-python
Dynamic: summary
